LinuxNeihe011WanquanZhushiXiuzhengbanV195/README.md
LinuxNeihe011WanquanZhushiXiuzhengbanV195/__init__.py
LinuxNeihe011WanquanZhushiXiuzhengbanV195/__main__.py
LinuxNeihe011WanquanZhushiXiuzhengbanV195/file.pdf
LinuxNeihe011WanquanZhushiXiuzhengbanV195/index.html
linux_neihe_0_11_wanquan_zhushi_xiuzhengban_v1_9_5-2024.2.29.0.dist-info/METADATA
linux_neihe_0_11_wanquan_zhushi_xiuzhengban_v1_9_5-2024.2.29.0.dist-info/WHEEL
linux_neihe_0_11_wanquan_zhushi_xiuzhengban_v1_9_5-2024.2.29.0.dist-info/entry_points.txt
linux_neihe_0_11_wanquan_zhushi_xiuzhengban_v1_9_5-2024.2.29.0.dist-info/top_level.txt
linux_neihe_0_11_wanquan_zhushi_xiuzhengban_v1_9_5-2024.2.29.0.dist-info/RECORD
